pytest_xstress.py
pytest_xstress-1.0.1.dist-info/METADATA
pytest_xstress-1.0.1.dist-info/WHEEL
pytest_xstress-1.0.1.dist-info/entry_points.txt
pytest_xstress-1.0.1.dist-info/RECORD
