Metadata-Version: 2.1
Name: pytest-xstress
Version: 1.0.1
Summary: 
Author: Yuvalino
Author-email: yuvalino@gmail.com
Requires-Python: >=3.8,<4.0
Classifier: Programming Language :: Python :: 3
Classifier: Programming Language :: Python :: 3.8
Classifier: Programming Language :: Python :: 3.9
Classifier: Programming Language :: Python :: 3.10
Classifier: Programming Language :: Python :: 3.11
Classifier: Programming Language :: Python :: 3.12
Requires-Dist: pytest (>=8.0.0,<9.0.0)
Requires-Dist: pytest-xdist (>=3.6.1,<4.0.0)
